udemyscraper/__init__.py
udemyscraper/metadata.py
udemyscraper/udscraperscript.py
udemyscraper/utils.py
udemyscraper/export/__init__.py
udemyscraper/export/csv.py
udemyscraper/export/dict.py
udemyscraper/export/json.py
udemyscraper/export/print.py
udemyscraper/export/xml.py
udemyscraper-0.8.1.dist-info/LICENSE.txt
udemyscraper-0.8.1.dist-info/METADATA
udemyscraper-0.8.1.dist-info/WHEEL
udemyscraper-0.8.1.dist-info/entry_points.txt
udemyscraper-0.8.1.dist-info/top_level.txt
udemyscraper-0.8.1.dist-info/RECORD
