Metadata-Version: 2.1
Name: udemyscraper
Version: 0.8.1
Summary: A Udemy Course Scraper built with beautiful soup, that fetches udemy course information. Get udemy course information and convert it to json, csv or xml file, without authentication.
Home-page: https://github.com/sortedcord/udemy-web-scraper
Author: Aditya Gupta
Author-email: divyashgupta2005@gmail.com
License: UNKNOWN
Project-URL: Bug Tracker, https://github.com/sortedcord/udemy-web-scraper/issues
Platform: UNKNOWN
Classifier: Programming Language :: Python :: 3
Classifier: Programming Language :: Python :: 3.9
Classifier: Programming Language :: Python :: 3.8
Classifier: License :: OSI Approved :: MIT License
Classifier: Operating System :: OS Independent
Classifier: Development Status :: 4 - Beta
Requires-Dist: alive-progress (==1.6.2)
Requires-Dist: appdirs (==1.4.4)
Requires-Dist: beautifulsoup4 (==4.9.3)
Requires-Dist: bs4 (==0.0.1)
Requires-Dist: certifi (==2021.5.30)
Requires-Dist: charset-normalizer (==2.0.4)
Requires-Dist: colorama (==0.4.4)
Requires-Dist: configparser (==5.0.2)
Requires-Dist: crayons (==0.4.0)
Requires-Dist: cssselect (==1.1.0)
Requires-Dist: fake-useragent (==0.1.11)
Requires-Dist: getopt2 (==0.0.3)
Requires-Dist: idna (==3.2)
Requires-Dist: lxml (==4.6.3)
Requires-Dist: pyee (==8.2.2)
Requires-Dist: pyquery (==1.4.3)
Requires-Dist: requests (==2.26.0)
Requires-Dist: selenium (==3.141.0)
Requires-Dist: soupsieve (==2.2.1)
Requires-Dist: tqdm (==4.62.2)
Requires-Dist: urllib3 (==1.26.6)
Requires-Dist: webdriver-manager (==3.4.2)
Requires-Dist: msedge-selenium-tools (==3.141.3)
Requires-Dist: dict2xml (==1.7.0)
Requires-Dist: dicttoxml (==1.7.4)
Provides-Extra: dev
Requires-Dist: pytest (>=3.7) ; extra == 'dev'
